{
    "secne": {
        "m_GameObject[0]": [],
        "m_GameObject[1]": [
            {
                "polymorphic_id": 1073741824,
                "ptr_wrapper": {
                    "valid": 1,
                    "data": {
                        "m_ObjctName": "cmaera",
                        "m_Component": [
                            {
                                "polymorphic_id": 2147483649,
                                "polymorphic_name": "Transform",
                                "ptr_wrapper": {
                                    "valid": 1,
                                    "data": {
                                        "m_Position": {
                                            "x": 0.0,
                                            "y": 5.0,
                                            "z": -10.0
                                        },
                                        "m_Rotation": {
                                            "x": 0.0,
                                            "y": 0.0,
                                            "z": 0.0
                                        },
                                        "m_Scale": {
                                            "x": 1.0,
                                            "y": 1.0,
                                            "z": 1.0
                                        }
                                    }
                                }
                            },
                            {
                                "polymorphic_id": 2147483650,
                                "polymorphic_name": "Camera",
                                "ptr_wrapper": {
                                    "valid": 1,
                                    "data": {}
                                }
                            }
                        ]
                    }
                }
            },
            {
                "polymorphic_id": 1073741824,
                "ptr_wrapper": {
                    "valid": 1,
                    "data": {
                        "m_ObjctName": "Player",
                        "m_Component": [
                            {
                                "polymorphic_id": 1,
                                "ptr_wrapper": {
                                    "valid": 1,
                                    "data": {
                                        "m_Position": {
                                            "x": -5.0,
                                            "y": 0.0,
                                            "z": 9.0
                                        },
                                        "m_Rotation": {
                                            "x": 0.0,
                                            "y": 0.0,
                                            "z": 0.0
                                        },
                                        "m_Scale": {
                                            "x": 1.0,
                                            "y": 1.0,
                                            "z": 1.0
                                        }
                                    }
                                }
                            },
                            {
                                "polymorphic_id": 2147483651,
                                "polymorphic_name": "Mesh",
                                "ptr_wrapper": {
                                    "valid": 1,
                                    "data": {
                                        "m_Modelpas": "box.obj",
                                        "m_Material": {
                                            "m_NameVS": "vertexLightingVS.cso",
                                            "m_NamePS": "vertexLightingPS.cso"
                                        }
                                    }
                                }
                            },
                            {
                                "polymorphic_id": 2147483652,
                                "polymorphic_name": "InputSystem",
                                "ptr_wrapper": {
                                    "valid": 1,
                                    "data": {
                                        "m_ObjectName": "Player"
                                    }
                                }
                            }
                        ]
                    }
                }
            },
            {
                "polymorphic_id": 1073741824,
                "ptr_wrapper": {
                    "valid": 1,
                    "data": {
                        "m_ObjctName": "Plane",
                        "m_Component": [
                            {
                                "polymorphic_id": 1,
                                "ptr_wrapper": {
                                    "valid": 1,
                                    "data": {
                                        "m_Position": {
                                            "x": 0.0,
                                            "y": 0.0,
                                            "z": 0.0
                                        },
                                        "m_Rotation": {
                                            "x": 0.0,
                                            "y": 0.0,
                                            "z": 0.0
                                        },
                                        "m_Scale": {
                                            "x": 1.0,
                                            "y": 1.0,
                                            "z": 1.0
                                        }
                                    }
                                }
                            },
                            {
                                "polymorphic_id": 2147483653,
                                "polymorphic_name": "Plane",
                                "ptr_wrapper": {
                                    "valid": 1,
                                    "data": {
                                        "m_ObjectName": "Plane"
                                    }
                                }
                            }
                        ]
                    }
                }
            },
            {
                "polymorphic_id": 1073741824,
                "ptr_wrapper": {
                    "valid": 1,
                    "data": {
                        "m_ObjctName": "GameObject(1)",
                        "m_Component": [
                            {
                                "polymorphic_id": 1,
                                "ptr_wrapper": {
                                    "valid": 1,
                                    "data": {
                                        "m_Position": {
                                            "x": 5.0,
                                            "y": 1.0,
                                            "z": 5.0
                                        },
                                        "m_Rotation": {
                                            "x": 0.0,
                                            "y": 0.0,
                                            "z": 0.0
                                        },
                                        "m_Scale": {
                                            "x": 1.0,
                                            "y": 1.0,
                                            "z": 1.0
                                        }
                                    }
                                }
                            },
                            {
                                "polymorphic_id": 3,
                                "ptr_wrapper": {
                                    "valid": 1,
                                    "data": {
                                        "m_Modelpas": "torus.obj",
                                        "m_Material": {
                                            "m_NameVS": "shadowVS.cso",
                                            "m_NamePS": "shadowPS.cso"
                                        }
                                    }
                                }
                            }
                        ]
                    }
                }
            }
        ],
        "m_GameObject[2]": [],
        "m_Name": "shadow"
    }
}